pycommremover/__init__.py
pycommremover-0.2.dist-info/LICENSE
pycommremover-0.2.dist-info/METADATA
pycommremover-0.2.dist-info/WHEEL
pycommremover-0.2.dist-info/top_level.txt
pycommremover-0.2.dist-info/RECORD
