Metadata-Version: 2.1
Name: pycommremover
Version: 0.2
Summary: Library to remove block and line comments.
Author-email: "Carlos A. Planchón" <carlosandresplanchonprestes@gmail.com>, Agustín Céspedes <agustinces17@gmail.com>
License: MIT License
Project-URL: repository, https://github.com/carlosplanchon/pycommremover.git
Keywords: comment,remover
Classifier: Intended Audience :: Developers
Classifier: Topic :: Software Development :: Build Tools
Classifier: License :: OSI Approved :: MIT License
Classifier: Programming Language :: Python :: 3.11
License-File: LICENSE
